README.txt
setup.py
mast_test/__init__.py
mast_test.egg-info/PKG-INFO
mast_test.egg-info/SOURCES.txt
mast_test.egg-info/dependency_links.txt
mast_test.egg-info/not-zip-safe
mast_test.egg-info/top_level.txt