Metadata-Version: 1.0
Name: mast-test
Version: 0.1
Summary: Package upload test
Home-page: https://github.com/MLman/pypitest.git
Author: Hyunwoo Kim
Author-email: noemailplz@gmail.com
License: MIT
Platform: UNKNOWN
